LICENSE
MANIFEST.in
README.rst
VERSION
setup.cfg
setup.py
sqlalchemy_utcdatetime.py
SQLAlchemy_UTCDateTime.egg-info/PKG-INFO
SQLAlchemy_UTCDateTime.egg-info/SOURCES.txt
SQLAlchemy_UTCDateTime.egg-info/dependency_links.txt
SQLAlchemy_UTCDateTime.egg-info/not-zip-safe
SQLAlchemy_UTCDateTime.egg-info/requires.txt
SQLAlchemy_UTCDateTime.egg-info/top_level.txt