Metadata-Version: 1.1
Name: SQLAlchemy-UTCDateTime
Version: 1.0.4
Summary: Convert to/from timezone aware datetimes when storing in a DBMS
Home-page: https://github.com/nickw444/SQLAlchemy-UTCDateTime
Author: Nick Whyte
Author-email: nick@nickwhyte.com
License: UNKNOWN
Platform: UNKNOWN
Classifier: Intended Audience :: Developers
Classifier: Programming Language :: Python
